[
  {
    "step": 62500,
    "raw": {
      "sum_rate": 0.5,
      "fairness": 0.2,
      "outage": -2.5,
      "queue": -0.4,
      "switching": -0.1
    },
    "clamped": {
      "sum_rate": 0.5,
      "fairness": 0.2,
      "outage": -1.5,
      "queue": -0.4,
      "switching": -0.1
    },
    "smoothed": {
      "sum_rate": 0.71,
      "fairness": 0.165,
      "outage": -0.8,
      "queue": -0.19,
      "switching": -0.065
    }
  },
  {
    "step": 187500,
    "raw": {
      "sum_rate": 0.5,
      "fairness": 0.15,
      "outage": -2.5,
      "switching": -0.05,
      "queue": -0.4
    },
    "clamped": {
      "sum_rate": 0.5,
      "fairness": 0.15,
      "outage": -1.5,
      "switching": -0.05,
      "queue": -0.4
    },
    "smoothed": {
      "sum_rate": 0.647,
      "fairness": 0.16,
      "outage": -1.01,
      "switching": -0.06,
      "queue": -0.253
    }
  },
  {
    "step": 312500,
    "raw": {
      "sum_rate": 0.85,
      "fairness": 0.15,
      "outage": -0.5,
      "switching": -0.05,
      "queue": -0.2
    },
    "clamped": {
      "sum_rate": 0.85,
      "fairness": 0.15,
      "outage": -0.5,
      "switching": -0.05,
      "queue": -0.2
    },
    "smoothed": {
      "sum_rate": 0.708,
      "fairness": 0.157,
      "outage": -0.857,
      "switching": -0.057,
      "queue": -0.237
    }
  },
  {
    "step": 437500,
    "raw": {
      "sum_rate": 0.85,
      "fairness": 0.15,
      "outage": -0.8,
      "switching": -0.05,
      "queue": -0.15
    },
    "clamped": {
      "sum_rate": 0.85,
      "fairness": 0.15,
      "outage": -0.8,
      "switching": -0.05,
      "queue": -0.15
    },
    "smoothed": {
      "sum_rate": 0.751,
      "fairness": 0.155,
      "outage": -0.84,
      "switching": -0.055,
      "queue": -0.211
    }
  }
]